chunk2milvus_hq/__init__.py
chunk2milvus_hq/embedding.py
chunk2milvus_hq/milvus_client.py
chunk2milvus_hq-0.1.0.dist-info/METADATA
chunk2milvus_hq-0.1.0.dist-info/WHEEL
chunk2milvus_hq-0.1.0.dist-info/top_level.txt
chunk2milvus_hq-0.1.0.dist-info/RECORD
