Metadata-Version: 2.4
Name: chunk2milvus-hq
Version: 0.1.0
Summary: Add your description here
Requires-Python: >=3.10
Requires-Dist: pymilvus>=2.3.0
Requires-Dist: openai>=1.0.0
Requires-Dist: python-dotenv>=1.0.0
Requires-Dist: fastchunker-hq>=0.1.0
